filometro/__init__.py
filometro/dataclasses.py
filometro/deolhonafila.py
filometro/enums.py
filometro/exceptions.py
filometro/filometro.py
filometro-1.3.0.dist-info/LICENSE
filometro-1.3.0.dist-info/METADATA
filometro-1.3.0.dist-info/WHEEL
filometro-1.3.0.dist-info/top_level.txt
filometro-1.3.0.dist-info/RECORD
