Metadata-Version: 2.1
Name: filometro
Version: 1.3.0
Summary: Obtenha os dados dos postos de vacinação da covid-19 em São Paulo
Home-page: https://github.com/matheusfelipeog/filometro
Author: Matheus Felipe
Author-email: matheusfelipeog@protonmail.com
License: MIT License
Project-URL: Bug Tracker, https://github.com/matheusfelipeog/filometro/issues
Project-URL: Documentation, https://github.com/matheusfelipeog/filometro/tree/master#documentação
Project-URL: Source Code, https://github.com/matheusfelipeog/filometro
Keywords: filometro,de-olho-na-fila,data,sao-paulo,covid-19,vacina,vacinasampa,python,wrapper,coronavirus
Classifier: Development Status :: 5 - Production/Stable
Classifier: Intended Audience :: Developers
Classifier: Intended Audience :: Information Technology
Classifier: License :: OSI Approved :: MIT License
Classifier: Natural Language :: Portuguese (Brazilian)
Classifier: Operating System :: OS Independent
Classifier: Programming Language :: Python
Classifier: Programming Language :: Python :: 3.7
Classifier: Programming Language :: Python :: 3.8
Classifier: Programming Language :: Python :: 3.9
Classifier: Programming Language :: Python :: 3.10
Classifier: Programming Language :: Python :: Implementation :: CPython
Classifier: Topic :: Software Development :: Libraries
Classifier: Topic :: Software Development :: Libraries :: Python Modules
Requires-Python: >=3.7
License-File: LICENSE
Requires-Dist: requests >=2.27.1
